anemoi/__init__.py
anemoi/cli.py
anemoi/client.py
anemoi/operator.py
anemoi/server.py
anemoi/util.py
anemoi/backends/__init__.py
anemoi/backends/database.py
anemoi/backends/tinydb.py
anemoi/providers/__init__.py
anemoi/providers/cloudflare.py
anemoi/providers/porkbun.py
anemoi_dns-1.0.5.dist-info/licenses/LICENSE
anemoi_dns-1.0.5.dist-info/METADATA
anemoi_dns-1.0.5.dist-info/WHEEL
anemoi_dns-1.0.5.dist-info/entry_points.txt
anemoi_dns-1.0.5.dist-info/top_level.txt
anemoi_dns-1.0.5.dist-info/RECORD
