Metadata-Version: 2.4
Name: anemoi-dns
Version: 1.0.5
Summary: A least privilege dynamic DNS server
Author-email: "Dayton Hasty (dayt0n)" <dayt0n@dayt0n.com>
Project-URL: Homepage, https://dayt0n.com/articles/anemoi/
Project-URL: Repository, https://github.com/dayt0n/anemoi
Project-URL: Issues, https://github.com/dayt0n/anemoi/issues
Keywords: dynamic,dns,least,privilege,zero trust
Classifier: Programming Language :: Python :: 3
Classifier: Operating System :: OS Independent
Classifier: License :: OSI Approved :: BSD License
Requires-Python: >=3.9
License-File: LICENSE
Requires-Dist: click
Requires-Dist: flask
Requires-Dist: arrow
Requires-Dist: requests
Requires-Dist: tinydb
Requires-Dist: cloudflare>=4.1.0
Requires-Dist: bcrypt
Requires-Dist: peewee
Requires-Dist: psycopg2
Requires-Dist: jsonschema
Requires-Dist: pyyaml
Dynamic: license-file
